lab1/collatz.sv
module collatz( input logic         clk,   // Clock
		input logic 	    go,    // Load value from n; start iterating
		input logic  [31:0] n,     // Start value; only read when go = 1
		output logic [31:0] dout,  // Iteration value: true after go = 1
		output logic 	    done); // True when dout reaches 1

reg [31:0] curr;
   /* Replace this comment and the code below with your solution */
   always_ff @(posedge clk) begin

   if(go == 1)
   begin
      curr <= n;
      dout <= 0;
      done <= 1'b0;
   end
   else
   begin
      if(curr == 1)
         begin
               done <= 1;
               dout <= curr;
               curr <= dout;
         end
      else
      begin
         if(curr%2 == 1)
            begin 
               done <= 0;
               dout <= 3*curr + 1;
               curr <= dout;
            end
         else
            begin
               done <= 0;
               dout <= curr/2;
               curr <= dout;
            end
         end
      end
   end
   /* Replace this comment and the code above with your solution */

endmodule

lab1/collatz.vcd
$version Generated by VerilatedVcd $end
$date Mon Jan 29 19:54:50 2024
 $end
$timescale   1ps $end

 $scope module TOP $end
  $var wire  1 # clk $end
  $var wire  1 ' done $end
  $var wire 32 & dout [31:0] $end
  $var wire  1 $ go $end
  $var wire 32 % n [31:0] $end
  $scope module collatz $end
   $var wire  1 # clk $end
   $var wire 32 ( curr [31:0] $end
   $var wire  1 ' done $end
   $var wire 32 & dout [31:0] $end
   $var wire  1 $ go $end
   $var wire 32 % n [31:0] $end
  $upscope $end
 $upscope $end
$enddefinitions $end


#0
0#
0$
b00000000000000000000000000000111 %
b00000000000000000000000000000000 &
0'
b00000000000000000000000000000000 (
#10
1#
#20
0#
1$
#30
1#
b00000000000000000000000000000111 (
#40
0#
#50
1#
#60
0#
0$
#70
1#
b00000000000000000000000000010110 &
b00000000000000000000000000000000 (
#80
0#
#90
1#
b00000000000000000000000000000000 &
b00000000000000000000000000010110 (
#100
0#
#110
1#
b00000000000000000000000000001011 &
b00000000000000000000000000000000 (
#120
0#
#130
1#
b00000000000000000000000000000000 &
b00000000000000000000000000001011 (
#140
0#
#150
1#
b00000000000000000000000000100010 &
b00000000000000000000000000000000 (
#160
0#
#170
1#
b00000000000000000000000000000000 &
b00000000000000000000000000100010 (
#180
0#
#190
1#
b00000000000000000000000000010001 &
b00000000000000000000000000000000 (
#200
0#
#210
1#
b00000000000000000000000000000000 &
b00000000000000000000000000010001 (
#220
0#
#230
1#
b00000000000000000000000000110100 &
b00000000000000000000000000000000 (
#240
0#
#250
1#
b00000000000000000000000000000000 &
b00000000000000000000000000110100 (
#260
0#
#270
1#
b00000000000000000000000000011010 &
b00000000000000000000000000000000 (
#280
0#
#290
1#
b00000000000000000000000000000000 &
b00000000000000000000000000011010 (
#300
0#
#310
1#
b00000000000000000000000000001101 &
b00000000000000000000000000000000 (
#320
0#
#330
1#
b00000000000000000000000000000000 &
b00000000000000000000000000001101 (
#340
0#
#350
1#
b00000000000000000000000000101000 &
b00000000000000000000000000000000 (
#360
0#
#370
1#
b00000000000000000000000000000000 &
b00000000000000000000000000101000 (
#380
0#
#390
1#
b00000000000000000000000000010100 &
b00000000000000000000000000000000 (
#400
0#
#410
1#
b00000000000000000000000000000000 &
b00000000000000000000000000010100 (
#420
0#
#430
1#
b00000000000000000000000000001010 &
b00000000000000000000000000000000 (
#440
0#
#450
1#
b00000000000000000000000000000000 &
b00000000000000000000000000001010 (
#460
0#
#470
1#
b00000000000000000000000000000101 &
b00000000000000000000000000000000 (
#480
0#
#490
1#
b00000000000000000000000000000000 &
b00000000000000000000000000000101 (
#500
0#
#510
1#
b00000000000000000000000000010000 &
b00000000000000000000000000000000 (
#520
0#
#530
1#
b00000000000000000000000000000000 &
b00000000000000000000000000010000 (
#540
0#
#550
1#
b00000000000000000000000000001000 &
b00000000000000000000000000000000 (
#560
0#
#570
1#
b00000000000000000000000000000000 &
b00000000000000000000000000001000 (
#580
0#
#590
1#
b00000000000000000000000000000100 &
b00000000000000000000000000000000 (
#600
0#
#610
1#
b00000000000000000000000000000000 &
b00000000000000000000000000000100 (
#620
0#
#630
1#
b00000000000000000000000000000010 &
b00000000000000000000000000000000 (
#640
0#
#650
1#
b00000000000000000000000000000000 &
b00000000000000000000000000000010 (
#660
0#
#670
1#
b00000000000000000000000000000001 &
b00000000000000000000000000000000 (
#680
0#
#690
1#
b00000000000000000000000000000000 &
b00000000000000000000000000000001 (
#700
0#
#710
1#
b00000000000000000000000000000001 &
1'
b00000000000000000000000000000000 (
#720
0#
#730
1#
b00000000000000000000000000000000 &
0'
b00000000000000000000000000000001 (
