lab1/collatz.sv
module collatz( input logic     	clk,   // Clock
   	 input logic     	go,	// Load value from n; start iterating
   	 input logic  [31:0] n, 	// Start value; only read when go = 1
   	 output logic [31:0] dout,  // Iteration value: true after go = 1
   	 output logic     	done); // True when dout reaches 1

   /* Replace this comment and the code below with your solution */
   always_ff @(posedge clk)
   begin
    if(go == 1)
    begin
        dout <= n;
        end
    else
    begin
        if(dout > 1)
        begin
            if(dout%2 == 1)
            begin
                dout <= 3*dout + 1;
            end
   			else
            begin
                dout <= dout/2;
            end
        end
    end
    end

assign done = (dout==1) ? 1'b1 : 1'b0;
/* Replace this comment and the code above with your solution */
endmodule

lab1/range.sv
module range
   #(parameter
     RAM_WORDS = 16,            // Number of counts to store in RAM
     RAM_ADDR_BITS = 4)         // Number of RAM address bits
   (input logic         clk,    // Clock
    input logic 	go,     // Read start and start testing
    input logic [31:0] 	start,  // Number to start from or count to read
    output logic 	done,   // True once memory is filled
    output logic [15:0] count); // Iteration count once finished

   logic 		cgo;    // "go" for the Collatz iterator
   logic                cdone;  // "done" from the Collatz iterator
   logic [31:0] 	n;      // number to start the Collatz iterator

// verilator lint_off PINCONNECTEMPTY
   
   // Instantiate the Collatz iterator
   collatz c1(.clk(clk),
	      .go(cgo),
	      .n(n),
	      .done(cdone),
	      .dout());

   logic [RAM_ADDR_BITS - 1:0] 	 num;         // The RAM address to write
   logic 			 running = 0; // True during the iterations
   /* Replace this comment and the code below with your solution,
      which should generate running, done, cgo, n, num, we, and din */
   assign done = cdone;
   // assign cgo = go;
   // assign n = start;
   // assign din = 16'h0;
   // assign num = 0;
   // assign we = running;   
   
   always_ff @(posedge clk) 
   begin
      if(go)
      begin
         running <= 1;
         n <= start;
         num <= 0;  
         cgo <= 1;
         din <= 1;    
      end
      if(cgo)  
      begin
         cgo <= 0;
      end

      if(running)
      begin
         if(we)  
         begin
            we <= 0;
         end

         if(cdone != 1)
         begin
         din <= din + 1;
         end

         else if (cdone)
         begin
         we <= 1;    
         n <= n+1;
         cgo <= 1;
         num <= num +   1;
         end
      end

   end

   /* Replace this comment and the code above with your solution */

   logic 			 we;                    // Write din to addr
   logic [15:0] 		 din;                   // Data to write
   logic [15:0] 		 mem[RAM_WORDS - 1:0];  // The RAM itself
   logic [RAM_ADDR_BITS - 1:0] 	 addr;                  // Address to read/write

   assign addr = we ? num : start[RAM_ADDR_BITS-1:0];
   
   always_ff @(posedge clk) begin
      if (we) mem[addr] <= din;
      count <= mem[addr];      
   end
endmodule

lab1/range.vcd
$version Generated by VerilatedVcd $end
$date Fri Feb  2 15:37:37 2024
 $end
$timescale   1ns $end

 $scope module TOP $end
  $var wire  1 /" clk $end
  $var wire 16 O" count [15:0] $end
  $var wire  1 G" done $end
  $var wire  1 7" go $end
  $var wire 32 ?" start [31:0] $end
  $scope module range $end
   $var wire 32 _" RAM_ADDR_BITS [31:0] $end
   $var wire 32 W" RAM_WORDS [31:0] $end
   $var wire  4 + addr [3:0] $end
   $var wire  1 ; cdone $end
   $var wire  1 3 cgo $end
   $var wire  1 /" clk $end
   $var wire 16 O" count [15:0] $end
   $var wire 16 [ din [15:0] $end
   $var wire  1 G" done $end
   $var wire  1 7" go $end
   $var wire 16 c mem(0) [15:0] $end
   $var wire 16 d mem(1) [15:0] $end
   $var wire 16 m mem(10) [15:0] $end
   $var wire 16 n mem(11) [15:0] $end
   $var wire 16 o mem(12) [15:0] $end
   $var wire 16 p mem(13) [15:0] $end
   $var wire 16 q mem(14) [15:0] $end
   $var wire 16 r mem(15) [15:0] $end
   $var wire 16 e mem(2) [15:0] $end
   $var wire 16 f mem(3) [15:0] $end
   $var wire 16 g mem(4) [15:0] $end
   $var wire 16 h mem(5) [15:0] $end
   $var wire 16 i mem(6) [15:0] $end
   $var wire 16 j mem(7) [15:0] $end
   $var wire 16 k mem(8) [15:0] $end
   $var wire 16 l mem(9) [15:0] $end
   $var wire 32 C n [31:0] $end
   $var wire  4 K num [3:0] $end
   $var wire  1 # running $end
   $var wire 32 ?" start [31:0] $end
   $var wire  1 S we $end
   $scope module c1 $end
    $var wire  1 /" clk $end
    $var wire  1 ; done $end
    $var wire 32 '" dout [31:0] $end
    $var wire  1 3 go $end
    $var wire 32 C n [31:0] $end
   $upscope $end
  $upscope $end
 $upscope $end
$enddefinitions $end


#0
0#
b0111 +
03
0;
b00000000000000000000000000000000 C
b0000 K
0S
b0000000000000000 [
b0000000000000000 c
b0000000000000000 d
b0000000000000000 e
b0000000000000000 f
b0000000000000000 g
b0000000000000000 h
b0000000000000000 i
b0000000000000000 j
b0000000000000000 k
b0000000000000000 l
b0000000000000000 m
b0000000000000000 n
b0000000000000000 o
b0000000000000000 p
b0000000000000000 q
b0000000000000000 r
b00000000000000000000000000000000 '"
0/"
17"
b00000000000000000000000000000111 ?"
0G"
b0000000000000000 O"
b00000000000000000000000000010000 W"
b00000000000000000000000000000100 _"
#10
1#
13
b00000000000000000000000000000111 C
b0000000000000001 [
1/"
#20
0/"
#30
03
b0000000000000010 [
b00000000000000000000000000000111 '"
1/"
#40
0/"
07"
#50
b0000000000000011 [
b00000000000000000000000000010110 '"
1/"
#60
0/"
#70
b0000000000000100 [
b00000000000000000000000000001011 '"
1/"
#80
0/"
#90
b0000000000000101 [
b00000000000000000000000000100010 '"
1/"
#100
0/"
#110
b0000000000000110 [
b00000000000000000000000000010001 '"
1/"
#120
0/"
#130
b0000000000000111 [
b00000000000000000000000000110100 '"
1/"
#140
0/"
#150
b0000000000001000 [
b00000000000000000000000000011010 '"
1/"
#160
0/"
#170
b0000000000001001 [
b00000000000000000000000000001101 '"
1/"
#180
0/"
#190
b0000000000001010 [
b00000000000000000000000000101000 '"
1/"
#200
0/"
#210
b0000000000001011 [
b00000000000000000000000000010100 '"
1/"
#220
0/"
#230
b0000000000001100 [
b00000000000000000000000000001010 '"
1/"
#240
0/"
#250
b0000000000001101 [
b00000000000000000000000000000101 '"
1/"
#260
0/"
#270
b0000000000001110 [
b00000000000000000000000000010000 '"
1/"
#280
0/"
#290
b0000000000001111 [
b00000000000000000000000000001000 '"
1/"
#300
0/"
#310
b0000000000010000 [
b00000000000000000000000000000100 '"
1/"
#320
0/"
#330
b0000000000010001 [
b00000000000000000000000000000010 '"
1/"
#340
0/"
#350
1;
b0000000000010010 [
b00000000000000000000000000000001 '"
1/"
1G"
#360
b0000 +
0/"
b00000000000000000000000000000000 ?"
#370
b0001 +
13
b00000000000000000000000000001000 C
b0001 K
1S
1/"
#380
0/"
b00000000000000000000000000000001 ?"
#390
b0010 +
0;
b00000000000000000000000000001001 C
b0010 K
b0000000000010010 d
b00000000000000000000000000001000 '"
1/"
0G"
#400
0/"
b00000000000000000000000000000010 ?"
#410
03
0S
b0000000000010011 [
b0000000000010010 e
b00000000000000000000000000001001 '"
1/"
#420
b0011 +
0/"
b00000000000000000000000000000011 ?"
#430
b0000000000010100 [
b00000000000000000000000000011100 '"
1/"
#440
b0100 +
0/"
b00000000000000000000000000000100 ?"
#450
b0000000000010101 [
b00000000000000000000000000001110 '"
1/"
#460
b0101 +
0/"
b00000000000000000000000000000101 ?"
#470
b0000000000010110 [
b00000000000000000000000000000111 '"
1/"
#480
b0110 +
0/"
b00000000000000000000000000000110 ?"
#490
b0000000000010111 [
b00000000000000000000000000010110 '"
1/"
#500
b0111 +
0/"
b00000000000000000000000000000111 ?"
#510
b0000000000011000 [
b00000000000000000000000000001011 '"
1/"
#520
b1000 +
0/"
b00000000000000000000000000001000 ?"
#530
b0000000000011001 [
b00000000000000000000000000100010 '"
1/"
#540
b1001 +
0/"
b00000000000000000000000000001001 ?"
#550
b0000000000011010 [
b00000000000000000000000000010001 '"
1/"
#560
b1010 +
0/"
b00000000000000000000000000001010 ?"
#570
b0000000000011011 [
b00000000000000000000000000110100 '"
1/"
#580
b1011 +
0/"
b00000000000000000000000000001011 ?"
#590
b0000000000011100 [
b00000000000000000000000000011010 '"
1/"
#600
b1100 +
0/"
b00000000000000000000000000001100 ?"
#610
b0000000000011101 [
b00000000000000000000000000001101 '"
1/"
#620
b1101 +
0/"
b00000000000000000000000000001101 ?"
#630
b0000000000011110 [
b00000000000000000000000000101000 '"
1/"
#640
b1110 +
0/"
b00000000000000000000000000001110 ?"
#650
b0000000000011111 [
b00000000000000000000000000010100 '"
1/"
#660
b1111 +
0/"
b00000000000000000000000000001111 ?"
#670
b0000000000100000 [
b00000000000000000000000000001010 '"
1/"
