lab1/collatz.sv
module collatz( input logic     	clk,   // Clock
   	 input logic     	go,	// Load value from n; start iterating
   	 input logic  [31:0] n, 	// Start value; only read when go = 1
   	 output logic [31:0] dout,  // Iteration value: true after go = 1
   	 output logic     	done); // True when dout reaches 1

   /* Replace this comment and the code below with your solution */
   always_ff @(posedge clk)
   begin
    if(go == 1)
    begin
        dout <= n;
        end
    else
    begin
        if(dout > 1)
        begin
            if(dout%2 == 1)
            begin
                dout <= 3*dout + 1;
            end
   			else
            begin
                dout <= dout/2;
            end
        end
    end
    end

assign done = (dout==1) ? 1'b1 : 1'b0;
/* Replace this comment and the code above with your solution */
endmodule

lab1/range.sv
module range
   #(parameter
   RAM_WORDS = 16,            // Number of counts to store in RAM
   RAM_ADDR_BITS = 4)         // Number of RAM address bits
   (input logic         clk,    // Clock
   input logic 	go,     // Read start and start testing
   input logic [31:0] 	start,  // Number to start from or count to read
   output logic 	done,   // True once memory is filled
   output logic [15:0] count); // Iteration count once finished

   logic 		cgo;    // "go" for the Collatz iterator
   logic                cdone;  // "done" from the Collatz iterator
   logic [31:0] 	n;      // number to start the Collatz iterator
   logic [31:0] 	dout_;      // number to start the Collatz iterator
   
   // verilator lint_off PINCONNECTEMPTY
   // Instantiate the Collatz iterator
   collatz c1(.clk(clk),
   .go(cgo),
   .n(n),
   .done(cdone),
   .dout(dout_));

   logic [RAM_ADDR_BITS - 1:0] 	 num;         // The RAM address to write
   logic 			 running = 0; // True during the iterations
   /* Replace this comment and the code below with your solution,
      which should generate running, done, cgo, n, num, we, and din */
   // assign done = cdone;
   // assign cgo = go;
   // assign n = start;
   // assign din = 16'h0;
   // assign num = 0;
   // assign we = running;   
   
   always_ff @(posedge clk) 
   begin
      if(go)
      begin
         running <= 1;
         n <= start;
//         num <= n[RAM_ADDR_BITS - 1:0]; //CHANGED  
         num <= 0;  
         cgo <= 1;
         din <= 1;    
         //addr<= 0;
      end
      
      if(done)  
      begin
         done <= 0;
      end
      
      if(cgo)  
      begin
         cgo <= 0;
         din <= 1;
      end

      if(we)
      begin 
         we <= 0;
         if(num != 2**RAM_ADDR_BITS - 1)
         begin
            cgo <= 1;
         end
         else
         begin
            cgo <= 0;
         end;
         
         if(num != 2**RAM_ADDR_BITS - 1)
         begin
            num <= num +   1;
         end
         
         n <= n+1;
         
         if(num == 2**RAM_ADDR_BITS - 1)
         begin
            running <= 0;
            done <= 1;
         end
      end

      if(running)
      begin
         if(dout_ == 2)
         begin
            we <= 1;
         end
         if(cdone == 0 && cgo == 0)
         begin
         din <= din + 1;
         end
      end
   end

   /* Replace this comment and the code above with your solution */
   //   logic 			 we_temp;                    // W	rite din to addr
   logic 			 we;                    // Write din to addr
   logic [15:0] 		 din;                   // Data to write
   logic [15:0] 		 mem[RAM_WORDS - 1:0];  // The RAM itself
   logic [RAM_ADDR_BITS - 1:0] 	 addr;                  // Address to read/write

   assign addr = we ? num : start[RAM_ADDR_BITS-1:0];
  //assign addr = we ? num : 0;
   
   always_ff @(posedge clk) begin
      if (we) mem[addr] <= din;
      count <= mem[addr];      
   end

endmodule

lab1/range.vcd
$version Generated by VerilatedVcd $end
$date Thu Feb  8 23:43:34 2024
 $end
$timescale   1ns $end

 $scope module TOP $end
  $var wire  1 /" clk $end
  $var wire 16 O" count [15:0] $end
  $var wire  1 G" done $end
  $var wire  1 7" go $end
  $var wire 32 ?" start [31:0] $end
  $scope module range $end
   $var wire 32 _" RAM_ADDR_BITS [31:0] $end
   $var wire 32 W" RAM_WORDS [31:0] $end
   $var wire  4 + addr [3:0] $end
   $var wire  1 ; cdone $end
   $var wire  1 3 cgo $end
   $var wire  1 /" clk $end
   $var wire 16 O" count [15:0] $end
   $var wire 16 c din [15:0] $end
   $var wire  1 G" done $end
   $var wire 32 K dout_ [31:0] $end
   $var wire  1 7" go $end
   $var wire 16 k mem(0) [15:0] $end
   $var wire 16 l mem(1) [15:0] $end
   $var wire 16 u mem(10) [15:0] $end
   $var wire 16 v mem(11) [15:0] $end
   $var wire 16 w mem(12) [15:0] $end
   $var wire 16 x mem(13) [15:0] $end
   $var wire 16 y mem(14) [15:0] $end
   $var wire 16 z mem(15) [15:0] $end
   $var wire 16 m mem(2) [15:0] $end
   $var wire 16 n mem(3) [15:0] $end
   $var wire 16 o mem(4) [15:0] $end
   $var wire 16 p mem(5) [15:0] $end
   $var wire 16 q mem(6) [15:0] $end
   $var wire 16 r mem(7) [15:0] $end
   $var wire 16 s mem(8) [15:0] $end
   $var wire 16 t mem(9) [15:0] $end
   $var wire 32 C n [31:0] $end
   $var wire  4 S num [3:0] $end
   $var wire  1 # running $end
   $var wire 32 ?" start [31:0] $end
   $var wire  1 [ we $end
   $scope module c1 $end
    $var wire  1 /" clk $end
    $var wire  1 ; done $end
    $var wire 32 K dout [31:0] $end
    $var wire  1 3 go $end
    $var wire 32 C n [31:0] $end
   $upscope $end
  $upscope $end
 $upscope $end
$enddefinitions $end


#0
0#
b0111 +
03
0;
b00000000000000000000000000000000 C
b00000000000000000000000000000000 K
b0000 S
0[
b0000000000000000 c
b0000000000000000 k
b0000000000000000 l
b0000000000000000 m
b0000000000000000 n
b0000000000000000 o
b0000000000000000 p
b0000000000000000 q
b0000000000000000 r
b0000000000000000 s
b0000000000000000 t
b0000000000000000 u
b0000000000000000 v
b0000000000000000 w
b0000000000000000 x
b0000000000000000 y
b0000000000000000 z
0/"
17"
b00000000000000000000000000000111 ?"
0G"
b0000000000000000 O"
b00000000000000000000000000010000 W"
b00000000000000000000000000000100 _"
#10
1#
13
b00000000000000000000000000000111 C
b0000000000000001 c
1/"
#20
0/"
#30
03
b00000000000000000000000000000111 K
1/"
#40
0/"
07"
#50
b00000000000000000000000000010110 K
b0000000000000010 c
1/"
#60
0/"
#70
b00000000000000000000000000001011 K
b0000000000000011 c
1/"
#80
0/"
#90
b00000000000000000000000000100010 K
b0000000000000100 c
1/"
#100
0/"
#110
b00000000000000000000000000010001 K
b0000000000000101 c
1/"
#120
0/"
#130
b00000000000000000000000000110100 K
b0000000000000110 c
1/"
#140
0/"
#150
b00000000000000000000000000011010 K
b0000000000000111 c
1/"
#160
0/"
#170
b00000000000000000000000000001101 K
b0000000000001000 c
1/"
#180
0/"
#190
b00000000000000000000000000101000 K
b0000000000001001 c
1/"
#200
0/"
#210
b00000000000000000000000000010100 K
b0000000000001010 c
1/"
#220
0/"
#230
b00000000000000000000000000001010 K
b0000000000001011 c
1/"
#240
0/"
#250
b00000000000000000000000000000101 K
b0000000000001100 c
1/"
#260
0/"
#270
b00000000000000000000000000010000 K
b0000000000001101 c
1/"
#280
0/"
#290
b00000000000000000000000000001000 K
b0000000000001110 c
1/"
#300
0/"
#310
b00000000000000000000000000000100 K
b0000000000001111 c
1/"
#320
0/"
#330
b00000000000000000000000000000010 K
b0000000000010000 c
1/"
#340
0/"
#350
b0000 +
1;
b00000000000000000000000000000001 K
1[
b0000000000010001 c
1/"
#360
0/"
#370
b0111 +
13
b00000000000000000000000000001000 C
b0001 S
0[
b0000000000010001 k
1/"
#380
0/"
#390
03
0;
b00000000000000000000000000001000 K
b0000000000000001 c
1/"
#400
0/"
#410
b00000000000000000000000000000100 K
b0000000000000010 c
1/"
#420
0/"
#430
b00000000000000000000000000000010 K
b0000000000000011 c
1/"
#440
0/"
#450
b0001 +
1;
b00000000000000000000000000000001 K
1[
b0000000000000100 c
1/"
#460
0/"
#470
b0111 +
13
b00000000000000000000000000001001 C
b0010 S
0[
b0000000000000100 l
1/"
#480
0/"
#490
03
0;
b00000000000000000000000000001001 K
b0000000000000001 c
1/"
#500
0/"
#510
b00000000000000000000000000011100 K
b0000000000000010 c
1/"
#520
0/"
#530
b00000000000000000000000000001110 K
b0000000000000011 c
1/"
#540
0/"
#550
b00000000000000000000000000000111 K
b0000000000000100 c
1/"
#560
0/"
#570
b00000000000000000000000000010110 K
b0000000000000101 c
1/"
#580
0/"
#590
b00000000000000000000000000001011 K
b0000000000000110 c
1/"
#600
0/"
#610
b00000000000000000000000000100010 K
b0000000000000111 c
1/"
#620
0/"
#630
b00000000000000000000000000010001 K
b0000000000001000 c
1/"
#640
0/"
#650
b00000000000000000000000000110100 K
b0000000000001001 c
1/"
#660
0/"
#670
b00000000000000000000000000011010 K
b0000000000001010 c
1/"
#680
0/"
#690
b00000000000000000000000000001101 K
b0000000000001011 c
1/"
#700
0/"
#710
b00000000000000000000000000101000 K
b0000000000001100 c
1/"
#720
0/"
#730
b00000000000000000000000000010100 K
b0000000000001101 c
1/"
#740
0/"
#750
b00000000000000000000000000001010 K
b0000000000001110 c
1/"
#760
0/"
#770
b00000000000000000000000000000101 K
b0000000000001111 c
1/"
#780
0/"
#790
b00000000000000000000000000010000 K
b0000000000010000 c
1/"
#800
0/"
#810
b00000000000000000000000000001000 K
b0000000000010001 c
1/"
#820
0/"
#830
b00000000000000000000000000000100 K
b0000000000010010 c
1/"
#840
0/"
#850
b00000000000000000000000000000010 K
b0000000000010011 c
1/"
#860
0/"
#870
b0010 +
1;
b00000000000000000000000000000001 K
1[
b0000000000010100 c
1/"
#880
0/"
#890
b0111 +
13
b00000000000000000000000000001010 C
b0011 S
0[
b0000000000010100 m
1/"
#900
0/"
#910
03
0;
b00000000000000000000000000001010 K
b0000000000000001 c
1/"
#920
0/"
#930
b00000000000000000000000000000101 K
b0000000000000010 c
1/"
#940
0/"
#950
b00000000000000000000000000010000 K
b0000000000000011 c
1/"
#960
0/"
#970
b00000000000000000000000000001000 K
b0000000000000100 c
1/"
#980
0/"
#990
b00000000000000000000000000000100 K
b0000000000000101 c
1/"
#1000
0/"
#1010
b00000000000000000000000000000010 K
b0000000000000110 c
1/"
#1020
0/"
#1030
b0011 +
1;
b00000000000000000000000000000001 K
1[
b0000000000000111 c
1/"
#1040
0/"
#1050
b0111 +
13
b00000000000000000000000000001011 C
b0100 S
0[
b0000000000000111 n
1/"
#1060
0/"
#1070
03
0;
b00000000000000000000000000001011 K
b0000000000000001 c
1/"
#1080
0/"
#1090
b00000000000000000000000000100010 K
b0000000000000010 c
1/"
#1100
0/"
#1110
b00000000000000000000000000010001 K
b0000000000000011 c
1/"
#1120
0/"
#1130
b00000000000000000000000000110100 K
b0000000000000100 c
1/"
#1140
0/"
#1150
b00000000000000000000000000011010 K
b0000000000000101 c
1/"
#1160
0/"
#1170
b00000000000000000000000000001101 K
b0000000000000110 c
1/"
#1180
0/"
#1190
b00000000000000000000000000101000 K
b0000000000000111 c
1/"
#1200
0/"
#1210
b00000000000000000000000000010100 K
b0000000000001000 c
1/"
#1220
0/"
#1230
b00000000000000000000000000001010 K
b0000000000001001 c
1/"
#1240
0/"
#1250
b00000000000000000000000000000101 K
b0000000000001010 c
1/"
#1260
0/"
#1270
b00000000000000000000000000010000 K
b0000000000001011 c
1/"
#1280
0/"
#1290
b00000000000000000000000000001000 K
b0000000000001100 c
1/"
#1300
0/"
#1310
b00000000000000000000000000000100 K
b0000000000001101 c
1/"
#1320
0/"
#1330
b00000000000000000000000000000010 K
b0000000000001110 c
1/"
#1340
0/"
#1350
b0100 +
1;
b00000000000000000000000000000001 K
1[
b0000000000001111 c
1/"
#1360
0/"
#1370
b0111 +
13
b00000000000000000000000000001100 C
b0101 S
0[
b0000000000001111 o
1/"
#1380
0/"
#1390
03
0;
b00000000000000000000000000001100 K
b0000000000000001 c
1/"
#1400
0/"
#1410
b00000000000000000000000000000110 K
b0000000000000010 c
1/"
#1420
0/"
#1430
b00000000000000000000000000000011 K
b0000000000000011 c
1/"
#1440
0/"
#1450
b00000000000000000000000000001010 K
b0000000000000100 c
1/"
#1460
0/"
#1470
b00000000000000000000000000000101 K
b0000000000000101 c
1/"
#1480
0/"
#1490
b00000000000000000000000000010000 K
b0000000000000110 c
1/"
#1500
0/"
#1510
b00000000000000000000000000001000 K
b0000000000000111 c
1/"
#1520
0/"
#1530
b00000000000000000000000000000100 K
b0000000000001000 c
1/"
#1540
0/"
#1550
b00000000000000000000000000000010 K
b0000000000001001 c
1/"
#1560
0/"
#1570
b0101 +
1;
b00000000000000000000000000000001 K
1[
b0000000000001010 c
1/"
#1580
0/"
#1590
b0111 +
13
b00000000000000000000000000001101 C
b0110 S
0[
b0000000000001010 p
1/"
#1600
0/"
#1610
03
0;
b00000000000000000000000000001101 K
b0000000000000001 c
1/"
#1620
0/"
#1630
b00000000000000000000000000101000 K
b0000000000000010 c
1/"
#1640
0/"
#1650
b00000000000000000000000000010100 K
b0000000000000011 c
1/"
#1660
0/"
#1670
b00000000000000000000000000001010 K
b0000000000000100 c
1/"
#1680
0/"
#1690
b00000000000000000000000000000101 K
b0000000000000101 c
1/"
#1700
0/"
#1710
b00000000000000000000000000010000 K
b0000000000000110 c
1/"
#1720
0/"
#1730
b00000000000000000000000000001000 K
b0000000000000111 c
1/"
#1740
0/"
#1750
b00000000000000000000000000000100 K
b0000000000001000 c
1/"
#1760
0/"
#1770
b00000000000000000000000000000010 K
b0000000000001001 c
1/"
#1780
0/"
#1790
b0110 +
1;
b00000000000000000000000000000001 K
1[
b0000000000001010 c
1/"
#1800
0/"
#1810
b0111 +
13
b00000000000000000000000000001110 C
b0111 S
0[
b0000000000001010 q
1/"
#1820
0/"
#1830
03
0;
b00000000000000000000000000001110 K
b0000000000000001 c
1/"
#1840
0/"
#1850
b00000000000000000000000000000111 K
b0000000000000010 c
1/"
#1860
0/"
#1870
b00000000000000000000000000010110 K
b0000000000000011 c
1/"
#1880
0/"
#1890
b00000000000000000000000000001011 K
b0000000000000100 c
1/"
#1900
0/"
#1910
b00000000000000000000000000100010 K
b0000000000000101 c
1/"
#1920
0/"
#1930
b00000000000000000000000000010001 K
b0000000000000110 c
1/"
#1940
0/"
#1950
b00000000000000000000000000110100 K
b0000000000000111 c
1/"
#1960
0/"
#1970
b00000000000000000000000000011010 K
b0000000000001000 c
1/"
#1980
0/"
#1990
b00000000000000000000000000001101 K
b0000000000001001 c
1/"
#2000
0/"
#2010
b00000000000000000000000000101000 K
b0000000000001010 c
1/"
#2020
0/"
#2030
b00000000000000000000000000010100 K
b0000000000001011 c
1/"
#2040
0/"
#2050
b00000000000000000000000000001010 K
b0000000000001100 c
1/"
#2060
0/"
#2070
b00000000000000000000000000000101 K
b0000000000001101 c
1/"
#2080
0/"
#2090
b00000000000000000000000000010000 K
b0000000000001110 c
1/"
#2100
0/"
#2110
b00000000000000000000000000001000 K
b0000000000001111 c
1/"
#2120
0/"
#2130
b00000000000000000000000000000100 K
b0000000000010000 c
1/"
#2140
0/"
#2150
b00000000000000000000000000000010 K
b0000000000010001 c
1/"
#2160
0/"
#2170
1;
b00000000000000000000000000000001 K
1[
b0000000000010010 c
1/"
#2180
0/"
#2190
13
b00000000000000000000000000001111 C
b1000 S
0[
b0000000000010010 r
1/"
#2200
0/"
#2210
03
0;
b00000000000000000000000000001111 K
b0000000000000001 c
1/"
b0000000000010010 O"
#2220
0/"
#2230
b00000000000000000000000000101110 K
b0000000000000010 c
1/"
#2240
0/"
#2250
b00000000000000000000000000010111 K
b0000000000000011 c
1/"
#2260
0/"
#2270
b00000000000000000000000001000110 K
b0000000000000100 c
1/"
#2280
0/"
#2290
b00000000000000000000000000100011 K
b0000000000000101 c
1/"
#2300
0/"
#2310
b00000000000000000000000001101010 K
b0000000000000110 c
1/"
#2320
0/"
#2330
b00000000000000000000000000110101 K
b0000000000000111 c
1/"
#2340
0/"
#2350
b00000000000000000000000010100000 K
b0000000000001000 c
1/"
#2360
0/"
#2370
b00000000000000000000000001010000 K
b0000000000001001 c
1/"
#2380
0/"
#2390
b00000000000000000000000000101000 K
b0000000000001010 c
1/"
#2400
0/"
#2410
b00000000000000000000000000010100 K
b0000000000001011 c
1/"
#2420
0/"
#2430
b00000000000000000000000000001010 K
b0000000000001100 c
1/"
#2440
0/"
#2450
b00000000000000000000000000000101 K
b0000000000001101 c
1/"
#2460
0/"
#2470
b00000000000000000000000000010000 K
b0000000000001110 c
1/"
#2480
0/"
#2490
b00000000000000000000000000001000 K
b0000000000001111 c
1/"
#2500
0/"
#2510
b00000000000000000000000000000100 K
b0000000000010000 c
1/"
#2520
0/"
#2530
b00000000000000000000000000000010 K
b0000000000010001 c
1/"
#2540
0/"
#2550
b1000 +
1;
b00000000000000000000000000000001 K
1[
b0000000000010010 c
1/"
#2560
0/"
#2570
b0111 +
13
b00000000000000000000000000010000 C
b1001 S
0[
b0000000000010010 s
1/"
b0000000000000000 O"
#2580
0/"
#2590
03
0;
b00000000000000000000000000010000 K
b0000000000000001 c
1/"
b0000000000010010 O"
#2600
0/"
#2610
b00000000000000000000000000001000 K
b0000000000000010 c
1/"
#2620
0/"
#2630
b00000000000000000000000000000100 K
b0000000000000011 c
1/"
#2640
0/"
#2650
b00000000000000000000000000000010 K
b0000000000000100 c
1/"
#2660
0/"
#2670
b1001 +
1;
b00000000000000000000000000000001 K
1[
b0000000000000101 c
1/"
#2680
0/"
#2690
b0111 +
13
b00000000000000000000000000010001 C
b1010 S
0[
b0000000000000101 t
1/"
b0000000000000000 O"
#2700
0/"
#2710
03
0;
b00000000000000000000000000010001 K
b0000000000000001 c
1/"
b0000000000010010 O"
#2720
0/"
#2730
b00000000000000000000000000110100 K
b0000000000000010 c
1/"
#2740
0/"
#2750
b00000000000000000000000000011010 K
b0000000000000011 c
1/"
#2760
0/"
#2770
b00000000000000000000000000001101 K
b0000000000000100 c
1/"
#2780
0/"
#2790
b00000000000000000000000000101000 K
b0000000000000101 c
1/"
#2800
0/"
#2810
b00000000000000000000000000010100 K
b0000000000000110 c
1/"
#2820
0/"
#2830
b00000000000000000000000000001010 K
b0000000000000111 c
1/"
#2840
0/"
#2850
b00000000000000000000000000000101 K
b0000000000001000 c
1/"
#2860
0/"
#2870
b00000000000000000000000000010000 K
b0000000000001001 c
1/"
#2880
0/"
#2890
b00000000000000000000000000001000 K
b0000000000001010 c
1/"
#2900
0/"
#2910
b00000000000000000000000000000100 K
b0000000000001011 c
1/"
#2920
0/"
#2930
b00000000000000000000000000000010 K
b0000000000001100 c
1/"
#2940
0/"
#2950
b1010 +
1;
b00000000000000000000000000000001 K
1[
b0000000000001101 c
1/"
#2960
0/"
#2970
b0111 +
13
b00000000000000000000000000010010 C
b1011 S
0[
b0000000000001101 u
1/"
b0000000000000000 O"
#2980
0/"
#2990
03
0;
b00000000000000000000000000010010 K
b0000000000000001 c
1/"
b0000000000010010 O"
#3000
0/"
#3010
b00000000000000000000000000001001 K
b0000000000000010 c
1/"
#3020
0/"
#3030
b00000000000000000000000000011100 K
b0000000000000011 c
1/"
#3040
0/"
#3050
b00000000000000000000000000001110 K
b0000000000000100 c
1/"
#3060
0/"
#3070
b00000000000000000000000000000111 K
b0000000000000101 c
1/"
#3080
0/"
#3090
b00000000000000000000000000010110 K
b0000000000000110 c
1/"
#3100
0/"
#3110
b00000000000000000000000000001011 K
b0000000000000111 c
1/"
#3120
0/"
#3130
b00000000000000000000000000100010 K
b0000000000001000 c
1/"
#3140
0/"
#3150
b00000000000000000000000000010001 K
b0000000000001001 c
1/"
#3160
0/"
#3170
b00000000000000000000000000110100 K
b0000000000001010 c
1/"
#3180
0/"
#3190
b00000000000000000000000000011010 K
b0000000000001011 c
1/"
#3200
0/"
#3210
b00000000000000000000000000001101 K
b0000000000001100 c
1/"
#3220
0/"
#3230
b00000000000000000000000000101000 K
b0000000000001101 c
1/"
#3240
0/"
#3250
b00000000000000000000000000010100 K
b0000000000001110 c
1/"
#3260
0/"
#3270
b00000000000000000000000000001010 K
b0000000000001111 c
1/"
#3280
0/"
#3290
b00000000000000000000000000000101 K
b0000000000010000 c
1/"
#3300
0/"
#3310
b00000000000000000000000000010000 K
b0000000000010001 c
1/"
#3320
0/"
#3330
b00000000000000000000000000001000 K
b0000000000010010 c
1/"
#3340
0/"
#3350
b00000000000000000000000000000100 K
b0000000000010011 c
1/"
#3360
0/"
#3370
b00000000000000000000000000000010 K
b0000000000010100 c
1/"
#3380
0/"
#3390
b1011 +
1;
b00000000000000000000000000000001 K
1[
b0000000000010101 c
1/"
#3400
0/"
#3410
b0111 +
13
b00000000000000000000000000010011 C
b1100 S
0[
b0000000000010101 v
1/"
b0000000000000000 O"
#3420
0/"
#3430
03
0;
b00000000000000000000000000010011 K
b0000000000000001 c
1/"
b0000000000010010 O"
#3440
0/"
#3450
b00000000000000000000000000111010 K
b0000000000000010 c
1/"
#3460
0/"
#3470
b00000000000000000000000000011101 K
b0000000000000011 c
1/"
#3480
0/"
#3490
b00000000000000000000000001011000 K
b0000000000000100 c
1/"
#3500
0/"
#3510
b00000000000000000000000000101100 K
b0000000000000101 c
1/"
#3520
0/"
#3530
b00000000000000000000000000010110 K
b0000000000000110 c
1/"
#3540
0/"
#3550
b00000000000000000000000000001011 K
b0000000000000111 c
1/"
#3560
0/"
#3570
b00000000000000000000000000100010 K
b0000000000001000 c
1/"
#3580
0/"
#3590
b00000000000000000000000000010001 K
b0000000000001001 c
1/"
#3600
0/"
#3610
b00000000000000000000000000110100 K
b0000000000001010 c
1/"
#3620
0/"
#3630
b00000000000000000000000000011010 K
b0000000000001011 c
1/"
#3640
0/"
#3650
b00000000000000000000000000001101 K
b0000000000001100 c
1/"
#3660
0/"
#3670
b00000000000000000000000000101000 K
b0000000000001101 c
1/"
#3680
0/"
#3690
b00000000000000000000000000010100 K
b0000000000001110 c
1/"
#3700
0/"
#3710
b00000000000000000000000000001010 K
b0000000000001111 c
1/"
#3720
0/"
#3730
b00000000000000000000000000000101 K
b0000000000010000 c
1/"
#3740
0/"
#3750
b00000000000000000000000000010000 K
b0000000000010001 c
1/"
#3760
0/"
#3770
b00000000000000000000000000001000 K
b0000000000010010 c
1/"
#3780
0/"
#3790
b00000000000000000000000000000100 K
b0000000000010011 c
1/"
#3800
0/"
#3810
b00000000000000000000000000000010 K
b0000000000010100 c
1/"
#3820
0/"
#3830
b1100 +
1;
b00000000000000000000000000000001 K
1[
b0000000000010101 c
1/"
#3840
0/"
#3850
b0111 +
13
b00000000000000000000000000010100 C
b1101 S
0[
b0000000000010101 w
1/"
b0000000000000000 O"
#3860
0/"
#3870
03
0;
b00000000000000000000000000010100 K
b0000000000000001 c
1/"
b0000000000010010 O"
#3880
0/"
#3890
b00000000000000000000000000001010 K
b0000000000000010 c
1/"
#3900
0/"
#3910
b00000000000000000000000000000101 K
b0000000000000011 c
1/"
#3920
0/"
#3930
b00000000000000000000000000010000 K
b0000000000000100 c
1/"
#3940
0/"
#3950
b00000000000000000000000000001000 K
b0000000000000101 c
1/"
#3960
0/"
#3970
b00000000000000000000000000000100 K
b0000000000000110 c
1/"
#3980
0/"
#3990
b00000000000000000000000000000010 K
b0000000000000111 c
1/"
#4000
0/"
#4010
b1101 +
1;
b00000000000000000000000000000001 K
1[
b0000000000001000 c
1/"
#4020
0/"
#4030
b0111 +
13
b00000000000000000000000000010101 C
b1110 S
0[
b0000000000001000 x
1/"
b0000000000000000 O"
#4040
0/"
#4050
03
0;
b00000000000000000000000000010101 K
b0000000000000001 c
1/"
b0000000000010010 O"
#4060
0/"
#4070
b00000000000000000000000001000000 K
b0000000000000010 c
1/"
#4080
0/"
#4090
b00000000000000000000000000100000 K
b0000000000000011 c
1/"
#4100
0/"
#4110
b00000000000000000000000000010000 K
b0000000000000100 c
1/"
#4120
0/"
#4130
b00000000000000000000000000001000 K
b0000000000000101 c
1/"
#4140
0/"
#4150
b00000000000000000000000000000100 K
b0000000000000110 c
1/"
#4160
0/"
#4170
b00000000000000000000000000000010 K
b0000000000000111 c
1/"
#4180
0/"
#4190
b1110 +
1;
b00000000000000000000000000000001 K
1[
b0000000000001000 c
1/"
#4200
0/"
#4210
b0111 +
13
b00000000000000000000000000010110 C
b1111 S
0[
b0000000000001000 y
1/"
b0000000000000000 O"
#4220
0/"
#4230
03
0;
b00000000000000000000000000010110 K
b0000000000000001 c
1/"
b0000000000010010 O"
#4240
0/"
#4250
b00000000000000000000000000001011 K
b0000000000000010 c
1/"
#4260
0/"
#4270
b00000000000000000000000000100010 K
b0000000000000011 c
1/"
#4280
0/"
#4290
b00000000000000000000000000010001 K
b0000000000000100 c
1/"
#4300
0/"
#4310
b00000000000000000000000000110100 K
b0000000000000101 c
1/"
#4320
0/"
#4330
b00000000000000000000000000011010 K
b0000000000000110 c
1/"
#4340
0/"
#4350
b00000000000000000000000000001101 K
b0000000000000111 c
1/"
#4360
0/"
#4370
b00000000000000000000000000101000 K
b0000000000001000 c
1/"
#4380
0/"
#4390
b00000000000000000000000000010100 K
b0000000000001001 c
1/"
#4400
0/"
#4410
b00000000000000000000000000001010 K
b0000000000001010 c
1/"
#4420
0/"
#4430
b00000000000000000000000000000101 K
b0000000000001011 c
1/"
#4440
0/"
#4450
b00000000000000000000000000010000 K
b0000000000001100 c
1/"
#4460
0/"
#4470
b00000000000000000000000000001000 K
b0000000000001101 c
1/"
#4480
0/"
#4490
b00000000000000000000000000000100 K
b0000000000001110 c
1/"
#4500
0/"
#4510
b00000000000000000000000000000010 K
b0000000000001111 c
1/"
#4520
0/"
#4530
b1111 +
1;
b00000000000000000000000000000001 K
1[
b0000000000010000 c
1/"
#4540
0/"
#4550
0#
b0111 +
b00000000000000000000000000010111 C
0[
b0000000000010000 z
1/"
1G"
b0000000000000000 O"
#4560
b0000 +
0/"
b00000000000000000000000000000000 ?"
#4570
1/"
0G"
b0000000000010001 O"
#4580
b0001 +
0/"
b00000000000000000000000000000001 ?"
#4590
1/"
b0000000000000100 O"
#4600
b0010 +
0/"
b00000000000000000000000000000010 ?"
#4610
1/"
b0000000000010100 O"
#4620
b0011 +
0/"
b00000000000000000000000000000011 ?"
#4630
1/"
b0000000000000111 O"
#4640
b0100 +
0/"
b00000000000000000000000000000100 ?"
#4650
1/"
b0000000000001111 O"
#4660
b0101 +
0/"
b00000000000000000000000000000101 ?"
#4670
1/"
b0000000000001010 O"
#4680
b0110 +
0/"
b00000000000000000000000000000110 ?"
#4690
1/"
#4700
b0111 +
0/"
b00000000000000000000000000000111 ?"
#4710
1/"
b0000000000010010 O"
#4720
b1000 +
0/"
b00000000000000000000000000001000 ?"
#4730
1/"
#4740
b1001 +
0/"
b00000000000000000000000000001001 ?"
#4750
1/"
b0000000000000101 O"
#4760
b1010 +
0/"
b00000000000000000000000000001010 ?"
#4770
1/"
b0000000000001101 O"
#4780
b1011 +
0/"
b00000000000000000000000000001011 ?"
#4790
1/"
b0000000000010101 O"
#4800
b1100 +
0/"
b00000000000000000000000000001100 ?"
#4810
1/"
#4820
b1101 +
0/"
b00000000000000000000000000001101 ?"
#4830
1/"
b0000000000001000 O"
#4840
b1110 +
0/"
b00000000000000000000000000001110 ?"
#4850
1/"
#4860
b1111 +
0/"
b00000000000000000000000000001111 ?"
#4870
1/"
b0000000000010000 O"
